{"_id":"4c88b3c77c1c3","_rev":"1-7a0a2c62ef7ba2a5744249acc653084b","questions":{"0":{"1":"","2":"","3":"","4":"","question":""},"1":{"1":"роман-писател","2":"палка-диригент","3":"училище - учител","4":"стихотворение -поема","question":"При коя от двойките думи има същото смислово отношение,както при двойката \"симфония-композитор\""},"2":{"1":"Черния цвят,който се наложи над шарените екипи ще бъде на мода и този сезон.","2":"черният ","3":"","4":"","question":"В кое изречение е допусната пунктоационна грешка???"},"3":{"1":"","2":"","3":"","4":"","question":""}},"appname":"Как си с българския","description":"Пробвай се","owner":"100000858605905","ownername":"Polina Spasova","ownerpic":"http://profile.ak.fbcdn.net/hprofile-ak-snc4/hs335.snc4/41702_100000858605905_4476_q.jpg","uid":"4c88b3c77c1c3","quiz":{"4c88b3c77b21f1":{"short":"Отлично","full":"Доста добре"},"4c88b3c77b6092":{"short":"Браво","full":""},"4c88b3c77b6093":{"short":"Емм с Малко грешки.. ","full":""},"4c88b3c77b6094":{"short":"Знаеш доста но ..","full":""}},"image":null}